vcsinfo/__init__.py
vcsinfo/__main__.py
vcsinfo/git.py
vcsinfo/hg.py
vcsinfo/perforce.py
vcsinfo/py_info.py
vcsinfo-2.2.116.dist-info/WHEEL
vcsinfo-2.2.116.dist-info/entry_points.txt
vcsinfo-2.2.116.dist-info/METADATA
vcsinfo-2.2.116.dist-info/RECORD
