Metadata-Version: 2.3
Name: vcsinfo
Version: 2.2.116
Summary: Utilities to normalize working with different Version Control Systems
Author: Adobe
Author-email: Adobe <noreply@adobe.com>
License: MIT
Classifier: Development Status :: 5 - Production/Stable
Classifier: License :: OSI Approved :: MIT License
Classifier: Operating System :: OS Independent
Classifier: Programming Language :: Python
Classifier: Programming Language :: Python :: 3
Classifier: Programming Language :: Python :: 3.8
Classifier: Programming Language :: Python :: 3.9
Classifier: Programming Language :: Python :: 3.10
Classifier: Programming Language :: Python :: 3.11
Requires-Dist: gitpython>=3.1
Requires-Dist: gitdb>=4
Requires-Dist: mercurial ; extra == 'hg'
Requires-Dist: p4python ; extra == 'p4'
Requires-Python: >=3.8
Project-URL: Homepage, https://github.com/adobe/vcsinfo
Provides-Extra: hg
Provides-Extra: p4
